aws_sso_credential_helper/__init__.py
aws_sso_credential_helper/__main__.py
aws_sso_credential_helper/credential_helper.py
aws_sso_credential_helper-1.0.0.dist-info/LICENSE
aws_sso_credential_helper-1.0.0.dist-info/METADATA
aws_sso_credential_helper-1.0.0.dist-info/WHEEL
aws_sso_credential_helper-1.0.0.dist-info/top_level.txt
aws_sso_credential_helper-1.0.0.dist-info/RECORD
