Metadata-Version: 2.1
Name: aws_sso_credential_helper
Version: 1.0.0
Home-page: https://github.com/nbtd/aws-sso-credential-helper
Author: nbtd
Author-email: baconss11@gmail.com
License: MIT
Keywords: aws sso credential helper
Classifier: License :: OSI Approved :: MIT License
Classifier: Programming Language :: Python :: 3.12
Requires-Python: >=3.6
License-File: LICENSE
Requires-Dist: boto3
